urbandictionary.py
urbandictpy-1.1.dist-info/LICENSE
urbandictpy-1.1.dist-info/METADATA
urbandictpy-1.1.dist-info/WHEEL
urbandictpy-1.1.dist-info/top_level.txt
urbandictpy-1.1.dist-info/RECORD
